operations/mathop.py
example_op-0.1.dist-info/LICENSE
example_op-0.1.dist-info/METADATA
example_op-0.1.dist-info/WHEEL
example_op-0.1.dist-info/top_level.txt
example_op-0.1.dist-info/RECORD
