Metadata-Version: 2.1
Name: example-op
Version: 0.1
Summary: A simple function for mathematical operations
Home-page: https://github.com/silenthunter007/test_pip
Author: Avishek Das
Author-email: avishek.das.ayan@gmail.com
License: MIT
Platform: UNKNOWN
Classifier: Programming Language :: Python :: 3
Classifier: License :: OSI Approved :: MIT License
Classifier: Operating System :: OS Independent
